MANIFEST.in
README.rst
requirements.txt
setup.py
CORDRobot/CORDDictUtils.py
CORDRobot/VERSION
CORDRobot/__init__.py
CORDRobot/restApi.py
CORDRobot/testCaseUtils.py
CORDRobot/rf-resources/ATTWorkFlowDriver.resource
CORDRobot/rf-resources/CIAB.resource
CORDRobot/rf-resources/DHCP.resource
CORDRobot/rf-resources/Kubernetes.resource
CORDRobot/rf-resources/Network.resource
CORDRobot/rf-resources/OLT.resource
CORDRobot/rf-resources/ONOS.resource
CORDRobot/rf-resources/ONU.resource
CORDRobot/rf-resources/Subscriber.resource
CORDRobot/rf-resources/XOS.resource
CORDRobot/rf-resources/utils.resource
cord_robot.egg-info/PKG-INFO
cord_robot.egg-info/SOURCES.txt
cord_robot.egg-info/dependency_links.txt
cord_robot.egg-info/requires.txt
cord_robot.egg-info/top_level.txt