Metadata-Version: 1.0
Name: cord-robot
Version: 2.1.3
Summary: CORD Project Robot Libraries and common Resources
Home-page: UNKNOWN
Author: CORD Developers
Author-email: UNKNOWN
License: UNKNOWN
Platform: UNKNOWN
